LICENSE
MANIFEST.in
README.md
setup.py
pyDOE2/__init__.py
pyDOE2/build_regression_matrix.py
pyDOE2/doe_box_behnken.py
pyDOE2/doe_composite.py
pyDOE2/doe_factorial.py
pyDOE2/doe_fold.py
pyDOE2/doe_gsd.py
pyDOE2/doe_lhs.py
pyDOE2/doe_plackett_burman.py
pyDOE2/doe_repeat_center.py
pyDOE2/doe_star.py
pyDOE2/doe_union.py
pyDOE2/var_regression_matrix.py
pyDOE2.egg-info/PKG-INFO
pyDOE2.egg-info/SOURCES.txt
pyDOE2.egg-info/dependency_links.txt
pyDOE2.egg-info/requires.txt
pyDOE2.egg-info/top_level.txt